dynamic_mcp/bpftrace_executor.py
dynamic_mcp/config.py
dynamic_mcp/crash_discovery.py
dynamic_mcp/crash_session.py
dynamic_mcp/dynamic-mcp.service
dynamic_mcp/kernel_detection.py
dynamic_mcp/permission_manager.py
dynamic_mcp/server.py
dynamic_mcp/systemd_installer.py
dynamic_mcp/tunnel_manager.py
dynamic_mcp-0.3.4.data/scripts/setup.py
dynamic_mcp-0.3.4.dist-info/licenses/LICENSE
dynamic_mcp-0.3.4.dist-info/METADATA
dynamic_mcp-0.3.4.dist-info/WHEEL
dynamic_mcp-0.3.4.dist-info/entry_points.txt
dynamic_mcp-0.3.4.dist-info/top_level.txt
dynamic_mcp-0.3.4.dist-info/RECORD
