Metadata-Version: 2.4
Name: dynamic-mcp
Version: 0.3.4
Summary: MCP server for dynamic analysys: BPFtrace, crash dump
Author-email: 42Research Ltd <software@42research.co.uk>
License: MIT
Project-URL: Homepage, https://42Research.co.uk
Project-URL: Repository, https://github.com/42Research/dynamic_mcp
Project-URL: Documentation, https://github.com/42Research/dynamic_mcp/wiki
Project-URL: Issues, https://github.com/42Research/dynamic_mcp/issues
Keywords: mcp,dynamic,bpftrace,crash,analysis,debugging,kernel
Classifier: Development Status :: 4 - Beta
Classifier: Intended Audience :: Developers
Classifier: Intended Audience :: System Administrators
Classifier: License :: OSI Approved :: MIT License
Classifier: Operating System :: POSIX :: Linux
Classifier: Programming Language :: Python :: 3
Classifier: Programming Language :: Python :: 3.10
Classifier: Programming Language :: Python :: 3.11
Classifier: Programming Language :: Python :: 3.12
Classifier: Topic :: Software Development :: Debuggers
Classifier: Topic :: System :: Monitoring
Requires-Python: >=3.10
License-File: LICENSE
Requires-Dist: mcp>=1.0.0
Requires-Dist: uvicorn>=0.24.0
Requires-Dist: starlette>=0.27.0
Requires-Dist: pydantic>=2.0.0
Requires-Dist: python-dotenv>=1.0.0
Requires-Dist: pexpect>=4.8.0
Requires-Dist: psutil>=5.9.0
Requires-Dist: python-dateutil>=2.8.0
Requires-Dist: aiohttp>=3.9.0
Dynamic: license-file
